infixpy/__init__.py
infixpy-0.0.4.dist-info/LICENSE
infixpy-0.0.4.dist-info/METADATA
infixpy-0.0.4.dist-info/WHEEL
infixpy-0.0.4.dist-info/top_level.txt
infixpy-0.0.4.dist-info/RECORD
