Metadata-Version: 2.1
Name: infixpy
Version: 0.0.4
Summary: Infix data structures for Python
Home-page: https://github.com/sboesch/infixpy
Author: Stephen Boesch based on original code form Matt Hagy 
Author-email: javadba@gmail.com
License: UNKNOWN
Platform: UNKNOWN
Classifier: Programming Language :: Python :: 3
Classifier: License :: OSI Approved :: MIT License
Classifier: Operating System :: OS Independent
